[
  {
    "index": 1,
    "word": "conqueror",
    "phonetic": "[ˈkɒŋkərə(r)]",
    "meanings": "n.征服者；占领者",
    "wrong": 0
  },
  {
    "index": 2,
    "word": "embark",
    "phonetic": "[ɪmˈbɑːk]",
    "meanings": "v.（使）上船或飞机；（使）从事",
    "wrong": 0
  },
  {
    "index": 3,
    "word": "cleanse",
    "phonetic": "[klenz]",
    "meanings": "v.使清洁；净化",
    "wrong": 0
  },
  {
    "index": 4,
    "word": "imaginary",
    "phonetic": "[ɪˈmædʒɪnəri]",
    "meanings": "adj.想象中的；虚构的",
    "wrong": 0
  },
  {
    "index": 5,
    "word": "television",
    "phonetic": "[ˈtelɪvɪʒ(ə)n]",
    "meanings": "n.电视机；电视节目；电视行业",
    "wrong": 0
  },
  {
    "index": 6,
    "word": "supporter",
    "phonetic": "[səˈpɔːtə(r)]",
    "meanings": "n.支持者；拥护者",
    "wrong": 0
  },
  {
    "index": 7,
    "word": "divorce",
    "phonetic": "[dɪˈvɔːs]",
    "meanings": "n.离婚；脱离； v.离婚；使脱离",
    "wrong": 0
  },
  {
    "index": 8,
    "word": "hierarchical",
    "phonetic": "[ˌhaɪəˈrɑːkɪk(ə)l]",
    "meanings": "adj.分等级的",
    "wrong": 0
  },
  {
    "index": 9,
    "word": "govern",
    "phonetic": "[ˈɡʌv(ə)n]",
    "meanings": "v.统治；治理；控制",
    "wrong": 0
  },
  {
    "index": 10,
    "word": "misfortune",
    "phonetic": "[ˌmɪsˈfɔːtʃuːn]",
    "meanings": "n.不幸；灾祸",
    "wrong": 0
  },
  {
    "index": 11,
    "word": "ahead",
    "phonetic": "[əˈhed]",
    "meanings": "adv.提前；在前",
    "wrong": 0
  },
  {
    "index": 12,
    "word": "mourning",
    "phonetic": "[ˈmɔːnɪŋ]",
    "meanings": "n.哀悼；悲痛；服丧； v.悼念；哀痛；“mourn”的现在分词",
    "wrong": 0
  },
  {
    "index": 13,
    "word": "determination",
    "phonetic": "[dɪˌtɜːmɪˈneɪʃ(ə)n]",
    "meanings": "n.决心；坚定；测定",
    "wrong": 0
  },
  {
    "index": 14,
    "word": "thinking",
    "phonetic": "[ˈθɪŋkɪŋ]",
    "meanings": "n.思想；想法； v.想；认为；“think”的现在分词",
    "wrong": 0
  },
  {
    "index": 15,
    "word": "list",
    "phonetic": "[lɪst]",
    "meanings": "n.表；名单； v.列出；（船）倾斜",
    "wrong": 0
  },
  {
    "index": 16,
    "word": "senior",
    "phonetic": "[ˈsiːniə(r)]",
    "meanings": "adj.高级的；年长的；资深的；n.上司；年长者；大四学生",
    "wrong": 0
  },
  {
    "index": 17,
    "word": "hamburger",
    "phonetic": "[ˈhæmbɜːɡə(r)]",
    "meanings": "n.汉堡包",
    "wrong": 0
  },
  {
    "index": 18,
    "word": "paint",
    "phonetic": "[peɪnt]",
    "meanings": "v.刷油漆；画；绘； n.油漆；绘画颜料",
    "wrong": 0
  },
  {
    "index": 19,
    "word": "defence",
    "phonetic": "[dɪˈfens]",
    "meanings": "n.防御；防守",
    "wrong": 0
  },
  {
    "index": 20,
    "word": "decisive",
    "phonetic": "[dɪˈsaɪsɪv]",
    "meanings": "adj.决定性的；果断的",
    "wrong": 0
  },
  {
    "index": 21,
    "word": "almighty",
    "phonetic": "[ɔːlˈmaɪti]",
    "meanings": "adj.全能的； 有无限权力的；很大的",
    "wrong": 0
  },
  {
    "index": 22,
    "word": "study",
    "phonetic": "[ˈstʌdi]",
    "meanings": "v.学习；研究； n.学习；研究；书房",
    "wrong": 0
  },
  {
    "index": 23,
    "word": "endorse",
    "phonetic": "[ɪnˈdɔːs]",
    "meanings": "v.签署；背书；支持；赞同",
    "wrong": 0
  },
  {
    "index": 24,
    "word": "dent",
    "phonetic": "[dent]",
    "meanings": "n.凹痕；挫伤；削弱； v.使…凹陷；削弱",
    "wrong": 0
  },
  {
    "index": 25,
    "word": "subsidy",
    "phonetic": "[ˈsʌbsədi]",
    "meanings": "n.补贴；津贴；补助金",
    "wrong": 0
  },
  {
    "index": 26,
    "word": "ward off evil spirits",
    "phonetic": "[wɔːd ɒf ˈiːv(ə)l ˈspɪrɪts]",
    "meanings": "phrase.驱邪避凶",
    "wrong": 0
  },
  {
    "index": 27,
    "word": "except",
    "phonetic": "[ɪkˈsept]",
    "meanings": "conj.除了；只是； v.不计；把…除外； prep.除了；除外",
    "wrong": 0
  },
  {
    "index": 28,
    "word": "easy",
    "phonetic": "[ˈiːzi]",
    "meanings": "adj.容易的；轻松的",
    "wrong": 0
  },
  {
    "index": 29,
    "word": "allergy",
    "phonetic": "[ˈælədʒi]",
    "meanings": "n.过敏症；反感；厌恶",
    "wrong": 0
  },
  {
    "index": 30,
    "word": "must",
    "phonetic": "[mʌst]",
    "meanings": "auxv.必须；一定要； n.必须做的事；必不可少的事物",
    "wrong": 0
  },
  {
    "index": 31,
    "word": "ﬂy",
    "phonetic": "[ﬂaɪ]",
    "meanings": "v.飞翔；飞行； n.苍蝇",
    "wrong": 0
  },
  {
    "index": 32,
    "word": "juicy",
    "phonetic": "[ˈdʒuːsi]",
    "meanings": "adj.多汁的；利润丰厚的；有趣味的",
    "wrong": 0
  },
  {
    "index": 33,
    "word": "coin",
    "phonetic": "[kɔɪn]",
    "meanings": "n.硬币；金属钱币； v.铸造硬币；杜撰；创造",
    "wrong": 0
  },
  {
    "index": 34,
    "word": "shipping",
    "phonetic": "[ˈʃɪpɪŋ]",
    "meanings": "n.船运；航运；船舶；运输；运送； v.装运；把…装上船；使乘船；在船上工作；“ship”的现在分词",
    "wrong": 0
  },
  {
    "index": 35,
    "word": "proverb",
    "phonetic": "[ˈprɒvɜːb]",
    "meanings": "n.谚语；格言",
    "wrong": 0
  },
  {
    "index": 36,
    "word": "strategy",
    "phonetic": "[ˈstrætədʒi]",
    "meanings": "n.策略；战略",
    "wrong": 0
  },
  {
    "index": 37,
    "word": "wither",
    "phonetic": "[ˈwɪðə(r)]",
    "meanings": "v.（使）枯萎；（使）衰弱",
    "wrong": 0
  },
  {
    "index": 38,
    "word": "dimensional",
    "phonetic": "[dɪˈmenʃənəl]",
    "meanings": "adj.维度的；空间的；尺寸的",
    "wrong": 0
  },
  {
    "index": 39,
    "word": "educational",
    "phonetic": "[ˌedʒuˈkeɪʃən(ə)l]",
    "meanings": "adj.教育的；有教育意义的",
    "wrong": 0
  },
  {
    "index": 40,
    "word": "atrocious",
    "phonetic": "[əˈtrəʊʃəs]",
    "meanings": "adj.残暴的；恶劣的；糟透的",
    "wrong": 0
  }
]