[
  {
    "index": 1,
    "word": "coexist",
    "phonetic": "[ˌkəʊɪɡˈzɪst]",
    "meanings": "v.共存；共处；和平共处",
    "wrong": 0
  },
  {
    "index": 2,
    "word": "trillion yuan",
    "phonetic": "[ˈtrɪljən juˈɑːn]",
    "meanings": "phrase.一万亿元",
    "wrong": 0
  },
  {
    "index": 3,
    "word": "dispel diseases",
    "phonetic": "[dɪˈspel dɪˈziːzɪz]",
    "meanings": "phrase.祛除疾病",
    "wrong": 0
  },
  {
    "index": 4,
    "word": "service outsourcing base",
    "phonetic": "[ˈsɜːvɪs ˈaʊtsɔːsɪŋ beɪs]",
    "meanings": "phrase.服务外包基地",
    "wrong": 0
  },
  {
    "index": 5,
    "word": "naturally",
    "phonetic": "[ˈnætʃrəli]",
    "meanings": "adv.自然地；理所当然地",
    "wrong": 0
  },
  {
    "index": 6,
    "word": "ago",
    "phonetic": "[əˈɡəʊ]",
    "meanings": "adv.以前",
    "wrong": 0
  },
  {
    "index": 7,
    "word": "skim",
    "phonetic": "[skɪm]",
    "meanings": "v.撇去；略读；掠过",
    "wrong": 0
  },
  {
    "index": 8,
    "word": "act",
    "phonetic": "[ækt]",
    "meanings": "v.行动；表现；演戏； n.行动；装模作样；（戏）幕；法令",
    "wrong": 0
  },
  {
    "index": 9,
    "word": "exposition",
    "phonetic": "[ˌekspəˈzɪʃ(ə)n]",
    "meanings": "n.博览会；展览会；阐述",
    "wrong": 0
  },
  {
    "index": 10,
    "word": "bunch",
    "phonetic": "[bʌntʃ]",
    "meanings": "n.束；串；捆；一群；一帮；一伙",
    "wrong": 0
  },
  {
    "index": 11,
    "word": "alternately",
    "phonetic": "[ɔːlˈtɜːnətli]",
    "meanings": "adv.交替地；隔一个地",
    "wrong": 0
  },
  {
    "index": 12,
    "word": "persuasion",
    "phonetic": "[pəˈsweɪʒ(ə)n]",
    "meanings": "n.说服；劝说",
    "wrong": 0
  },
  {
    "index": 13,
    "word": "astronomical",
    "phonetic": "[ˌæstrəˈnɒmɪk(ə)l]",
    "meanings": "adj.天文学的；巨大的",
    "wrong": 0
  },
  {
    "index": 14,
    "word": "doctoral",
    "phonetic": "[ˈdɒktərəl]",
    "meanings": "adj.博士的；博士学位的",
    "wrong": 0
  },
  {
    "index": 15,
    "word": "orphan",
    "phonetic": "[ˈɔːf(ə)n]",
    "meanings": "n.孤儿；失去生母的幼小动物",
    "wrong": 0
  },
  {
    "index": 16,
    "word": "contract",
    "phonetic": "[ˈkɒntrækt]",
    "meanings": "n.合同；契约； v.（使）收缩；订合同；感染",
    "wrong": 0
  },
  {
    "index": 17,
    "word": "raging",
    "phonetic": "[ˈreɪdʒɪŋ]",
    "meanings": "adj.狂怒的；猛烈的；狂暴的； v.发怒；怒斥；激烈进行；“rage”的现在分词",
    "wrong": 0
  },
  {
    "index": 18,
    "word": "resourceful",
    "phonetic": "[rɪˈsɔːsful]",
    "meanings": "adj.资源丰富的；机敏的；足智多谋的",
    "wrong": 0
  },
  {
    "index": 19,
    "word": "commercialize",
    "phonetic": "[kəˈmɜːʃəlaɪz]",
    "meanings": "v.使商业化；以…牟利",
    "wrong": 0
  },
  {
    "index": 20,
    "word": "see",
    "phonetic": "[siː]",
    "meanings": "v.看；领悟",
    "wrong": 0
  },
  {
    "index": 21,
    "word": "conventional",
    "phonetic": "[kənˈvenʃən(ə)l]",
    "meanings": "adj.传统的；惯例的",
    "wrong": 0
  },
  {
    "index": 22,
    "word": "attain",
    "phonetic": "[əˈteɪn]",
    "meanings": "v.达到；获得",
    "wrong": 0
  },
  {
    "index": 23,
    "word": "commendation",
    "phonetic": "[ˌkɒmenˈdeɪʃ(ə)n]",
    "meanings": "n.赞扬；称赞；荣誉；奖状",
    "wrong": 0
  },
  {
    "index": 24,
    "word": "large-scale expedition",
    "phonetic": "[lɑːdʒ skeɪl ˌekspəˈdɪʃ(ə)n]",
    "meanings": "phrase.大规模探险",
    "wrong": 0
  },
  {
    "index": 25,
    "word": "headmistress",
    "phonetic": "[ˌhedˈmɪstrəs]",
    "meanings": "n.女校长",
    "wrong": 0
  },
  {
    "index": 26,
    "word": "impulsive",
    "phonetic": "[ɪmˈpʌlsɪv]",
    "meanings": "adj.凭冲动行事的；易冲动的",
    "wrong": 0
  },
  {
    "index": 27,
    "word": "ﬁnally",
    "phonetic": "[ˈfaɪnəli]",
    "meanings": "adv.最后；终于",
    "wrong": 0
  },
  {
    "index": 28,
    "word": "distort",
    "phonetic": "[dɪˈstɔːt]",
    "meanings": "v.扭曲；歪曲；使变形",
    "wrong": 0
  },
  {
    "index": 29,
    "word": "depreciation",
    "phonetic": "[dɪˌpriːʃiˈeɪʃ(ə)n]",
    "meanings": "n.折旧；贬值；跌价",
    "wrong": 0
  },
  {
    "index": 30,
    "word": "bicycle",
    "phonetic": "[ˈbaɪsɪk(ə)l]",
    "meanings": "n.自行车；脚踏车",
    "wrong": 0
  },
  {
    "index": 31,
    "word": "gleam",
    "phonetic": "[ɡliːm]",
    "meanings": "v.闪烁；隐约闪现； n.亮光；闪光",
    "wrong": 0
  },
  {
    "index": 32,
    "word": "Olympic",
    "phonetic": "[əˈlɪmpɪk]",
    "meanings": "adj.奥林匹克的",
    "wrong": 0
  },
  {
    "index": 33,
    "word": "doze",
    "phonetic": "[dəʊz]",
    "meanings": "v.打瞌睡； n.瞌睡",
    "wrong": 0
  },
  {
    "index": 34,
    "word": "prescription",
    "phonetic": "[prɪˈskrɪpʃ(ə)n]",
    "meanings": "n.处方；药方",
    "wrong": 0
  },
  {
    "index": 35,
    "word": "trait",
    "phonetic": "[treɪt]",
    "meanings": "n.特性；特点",
    "wrong": 0
  },
  {
    "index": 36,
    "word": "suddenly",
    "phonetic": "[ˈsʌdənli]",
    "meanings": "adv.突然；猛然；骤然",
    "wrong": 0
  },
  {
    "index": 37,
    "word": "record",
    "phonetic": "[ˈrekɔːd]",
    "meanings": "n.记录；唱片； v.记录；录制",
    "wrong": 0
  },
  {
    "index": 38,
    "word": "millimeter",
    "phonetic": "[ˈmɪlimiːtə(r)]",
    "meanings": "n.毫米",
    "wrong": 0
  },
  {
    "index": 39,
    "word": "curse",
    "phonetic": "[kɜːs]",
    "meanings": "v.诅咒；咒骂； n.诅咒；咒骂",
    "wrong": 0
  },
  {
    "index": 40,
    "word": "ﬂour",
    "phonetic": "[ˈﬂaʊə(r)]",
    "meanings": "n.面粉",
    "wrong": 0
  }
]