[
  {
    "index": 1,
    "word": "lead",
    "phonetic": "[liːd]",
    "meanings": "v.领导；带领；导致； n.铅",
    "wrong": 0
  },
  {
    "index": 2,
    "word": "unique",
    "phonetic": "[juˈniːk]",
    "meanings": "adj.唯一的；独特的",
    "wrong": 0
  },
  {
    "index": 3,
    "word": "vulgar",
    "phonetic": "[ˈvʌlɡə(r)]",
    "meanings": "adj.庸俗的；粗俗的；粗野的；下流的",
    "wrong": 0
  },
  {
    "index": 4,
    "word": "and",
    "phonetic": "[ænd]",
    "meanings": "conj.和；与",
    "wrong": 0
  },
  {
    "index": 5,
    "word": "bicycle track",
    "phonetic": "[ˈbaɪsɪk(ə)l træk]",
    "meanings": "phrase.自行车路",
    "wrong": 0
  },
  {
    "index": 6,
    "word": "printing",
    "phonetic": "[ˈprɪntɪŋ]",
    "meanings": "n.印刷；印刷术； v.打印；印刷；“print”的现在分词",
    "wrong": 0
  },
  {
    "index": 7,
    "word": "clarity",
    "phonetic": "[ˈklærəti]",
    "meanings": "n.清楚；清晰；明确",
    "wrong": 0
  },
  {
    "index": 8,
    "word": "toil",
    "phonetic": "[tɔɪl]",
    "meanings": "v.费力地做；苦干；跋涉；n.苦工；劳累的工作",
    "wrong": 0
  },
  {
    "index": 9,
    "word": "geographic",
    "phonetic": "[ˌdʒɪəˈɡræfɪk]",
    "meanings": "adj.地理的；地理学的",
    "wrong": 0
  },
  {
    "index": 10,
    "word": "peel",
    "phonetic": "[piːl]",
    "meanings": "n.果皮； v.剥落；去皮",
    "wrong": 0
  },
  {
    "index": 11,
    "word": "tool",
    "phonetic": "[tuːl]",
    "meanings": "n.工具；刀具；器具； v.用工具加工",
    "wrong": 0
  },
  {
    "index": 12,
    "word": "attic",
    "phonetic": "[ˈætɪk]",
    "meanings": "n.阁楼；顶楼",
    "wrong": 0
  },
  {
    "index": 13,
    "word": "philosophical",
    "phonetic": "[ˌfɪləˈsɒfɪk(ə)l]",
    "meanings": "adj.哲学的；达观的",
    "wrong": 0
  },
  {
    "index": 14,
    "word": "bolt",
    "phonetic": "[bəʊlt]",
    "meanings": "n.插销；螺栓；闪电； v.用插销闩上",
    "wrong": 0
  },
  {
    "index": 15,
    "word": "predator",
    "phonetic": "[ˈpredətə(r)]",
    "meanings": "n.掠夺者；捕食性动物；食肉动物",
    "wrong": 0
  },
  {
    "index": 16,
    "word": "bill",
    "phonetic": "[bɪl]",
    "meanings": "n.账单；钞票；议案； v.给…开账单",
    "wrong": 0
  },
  {
    "index": 17,
    "word": "intense",
    "phonetic": "[ɪnˈtens]",
    "meanings": "adj.强烈的；剧烈的；紧张的",
    "wrong": 0
  },
  {
    "index": 18,
    "word": "identity",
    "phonetic": "[aɪˈdentəti]",
    "meanings": "n.身份；特性；一致",
    "wrong": 0
  },
  {
    "index": 19,
    "word": "safeguard",
    "phonetic": "[ˈseɪfɡɑːd]",
    "meanings": "n.保护措施； v.保卫；保护",
    "wrong": 0
  },
  {
    "index": 20,
    "word": "wound",
    "phonetic": "[wuːnd]",
    "meanings": "n.伤口；创伤； v.使受伤；伤害； v.蜿蜒；缠绕；“wind”的过去式和过去分词",
    "wrong": 0
  },
  {
    "index": 21,
    "word": "privileged",
    "phonetic": "[ˈprɪvəlɪdʒd]",
    "meanings": "adj.有特权的；特许的；保密的； v.给予…特权；“privilege”的过去式和过去分词",
    "wrong": 0
  },
  {
    "index": 22,
    "word": "sheep",
    "phonetic": "[ʃiːp]",
    "meanings": "n.绵羊；小羊；羔羊",
    "wrong": 0
  },
  {
    "index": 23,
    "word": "multinational company",
    "phonetic": "[ˌmʌltiˈnæʃnəl ˈkʌmpəni]",
    "meanings": "phrase.跨国公司",
    "wrong": 0
  },
  {
    "index": 24,
    "word": "vital",
    "phonetic": "[ˈvaɪt(ə)l]",
    "meanings": "adj.至关重要的；所必需的；生死攸关的；充满活力的",
    "wrong": 0
  },
  {
    "index": 25,
    "word": "pilgrim",
    "phonetic": "[ˈpɪlɡrɪm]",
    "meanings": "n.朝圣者",
    "wrong": 0
  },
  {
    "index": 26,
    "word": "run",
    "phonetic": "[rʌn]",
    "meanings": "v.跑步；经营； n.跑；运转",
    "wrong": 0
  },
  {
    "index": 27,
    "word": "folk religion",
    "phonetic": "[fəʊk rɪˈlɪdʒən]",
    "meanings": "phrase.民间信仰",
    "wrong": 0
  },
  {
    "index": 28,
    "word": "bright",
    "phonetic": "[braɪt]",
    "meanings": "adj.明亮的；鲜艳的；聪明的",
    "wrong": 0
  },
  {
    "index": 29,
    "word": "door",
    "phonetic": "[dɔː(r)]",
    "meanings": "n.门",
    "wrong": 0
  },
  {
    "index": 30,
    "word": "ﬂank",
    "phonetic": "[ﬂæŋk]",
    "meanings": "n.侧面；侧翼；胁腹； v.在…侧面（有）",
    "wrong": 0
  },
  {
    "index": 31,
    "word": "low",
    "phonetic": "[ləʊ]",
    "meanings": "adv.低；低矮；在低处；往下地； adj.低沉的；低垂的",
    "wrong": 0
  },
  {
    "index": 32,
    "word": "ghost",
    "phonetic": "[ɡəʊst]",
    "meanings": "n.鬼；幽灵",
    "wrong": 0
  },
  {
    "index": 33,
    "word": "undo",
    "phonetic": "[ʌnˈduː]",
    "meanings": "v.解开；撤销；毁掉",
    "wrong": 0
  },
  {
    "index": 34,
    "word": "simulation",
    "phonetic": "[ˌsɪmjuˈleɪʃ(ə)n]",
    "meanings": "n.模拟；仿真",
    "wrong": 0
  },
  {
    "index": 35,
    "word": "hypocrite",
    "phonetic": "[ˈhɪpəkrɪt]",
    "meanings": "n.伪君子；伪善者",
    "wrong": 0
  },
  {
    "index": 36,
    "word": "implication",
    "phonetic": "[ˌɪmplɪˈkeɪʃ(ə)n]",
    "meanings": "n.可能的影响（或后果）；暗示；含意；牵连",
    "wrong": 0
  },
  {
    "index": 37,
    "word": "hedge",
    "phonetic": "[hedʒ]",
    "meanings": "n.树篱；防范措施； v.用树篱围住；限制；避免",
    "wrong": 0
  },
  {
    "index": 38,
    "word": "ﬁlter",
    "phonetic": "[ˈfɪltə(r)]",
    "meanings": "n.过滤器； v.过滤",
    "wrong": 0
  },
  {
    "index": 39,
    "word": "assassinate",
    "phonetic": "[əˈsæsɪneɪt]",
    "meanings": "v.暗杀；行刺",
    "wrong": 0
  },
  {
    "index": 40,
    "word": "commune",
    "phonetic": "[ˈkɒmjuːn]",
    "meanings": "n.公社；亲密的会谈； v.亲密地交谈；与…融为一体",
    "wrong": 0
  }
]